ChangeLog
INSTALL
LICENSE
MANIFEST.in
README.rst
TODO
poppler-annotation.sip
poppler-convert.sip
poppler-document.sip
poppler-embedded-file.sip
poppler-font-info.sip
poppler-font-iterator.sip
poppler-form.sip
poppler-link-destination.sip
poppler-link.sip
poppler-media.sip
poppler-movie-object.sip
poppler-opt-content-model.sip
poppler-page-transition.sip
poppler-page.sip
poppler-qt5.sip
poppler-sound-object.sip
poppler-text-box.sip
project.py
pyproject.toml
setup.cfg
setup.py
timeline.sip
types.sip
version.sip.in
demo/demo.py
demo/merge-annotations.py
python_poppler_qt5.egg-info/PKG-INFO
python_poppler_qt5.egg-info/SOURCES.txt
python_poppler_qt5.egg-info/dependency_links.txt
python_poppler_qt5.egg-info/top_level.txt