Metadata-Version: 2.1
Name: python-poppler-qt5
Version: 21.3.0
Summary: A Python binding to Poppler-Qt5
Home-page: https://github.com/frescobaldi/python-poppler-qt5
Maintainer: Wilbert Berendsen
Maintainer-email: wbsoft@xs4all.nl
License: LGPL
Platform: UNKNOWN
Classifier: Development Status :: 5 - Production/Stable
Classifier: Intended Audience :: Developers
Classifier: License :: OSI Approved :: GNU Library or Lesser General Public License (LGPL)
Classifier: Operating System :: MacOS :: MacOS X
Classifier: Operating System :: Microsoft :: Windows
Classifier: Operating System :: POSIX
Classifier: Programming Language :: Python :: 3
Classifier: Topic :: Multimedia :: Graphics :: Viewers
License-File: LICENSE
